{
	"reference": {},
	"formula": {
		"0":  "M   20 0",
		"1":  "vl  -20 0",
		"2":  "l   200 {{xHeight}}",
		"3":  "vl  -20 0",
		"4":  "l   200 -{{xHeight}}",
		"5":  "vl   -20 0",
		"6":  "vL  {{ find({x: self[2].x, on: [self[5], self[3]] }) }}",
		"7":  "L   {{ find({y: xHeight / 2, on: [self[5], self[6]] }) }}",
		"8":  "L   {{ find({y: xHeight / 2, on: [self[0], self[6]] }) }}",
		"9":  "Z",
		"10": "M   {{ find({y: xHeight / 2 + 20, on: [self[5], self[6]] }) }}",
		"11": "L   {{ self[6].xy }}",
		"12": "L   {{ find({y: xHeight / 2 + 20, on: [self[0], self[6]] }) }}",
		"13": "Z",

		"after1": "serif {{ {side:'bottom-left', on:[self[1], self[2]] } }}",
		"before2": "serif {{ {side:'top-left', on:[self[2], self[1]] } }}",
		"after5": "serif {{ {side:'bottom-left', on:[self[5], self[7]] } }}"
	}
}